{
  "model_parameters": {
    "n_dimensions": 5,
    "n_clusters": 4,
    "n_points": 13,
    "coord_range_lower": -1,
    "coord_range_upper": 1
  },
  "solution": {
    "status": "optimal",
    "center_coordinates": {
      "cluster_1": {
        "dim_1": -0.325533422359912,
        "dim_2": 0.726991377748899,
        "dim_3": 0.327408325709949,
        "dim_4": 0.130413271309018,
        "dim_5": 0.801436989898524
      },
      "cluster_2": {
        "dim_1": -0.299934240832678,
        "dim_2": -0.332915998632449,
        "dim_3": 0.005779832319703,
        "dim_4": -0.729957987533455,
        "dim_5": -0.116806706379517
      },
      "cluster_3": {
        "dim_1": 0.37197828684348,
        "dim_2": 0.452348622096073,
        "dim_3": -0.025697817144329,
        "dim_4": 0.390195152689144,
        "dim_5": -0.605371829400926
      },
      "cluster_4": {
        "dim_1": 0.765167907132175,
        "dim_2": -0.399287662401896,
        "dim_3": 0.745920972257075,
        "dim_4": 0.728310764116633,
        "dim_5": 0.700444541149623
      }
    },
    "distances": {
      "1": 0.084535725063047,
      "2": 0.382675181074238,
      "3": 0.182982308205648,
      "4": 0.53594241809572,
      "5": 0.603071823741383,
      "6": 0.526543342527955,
      "7": 0.443001459819989,
      "8": 4.728593e-09,
      "9": 1.2202088296659,
      "10": 1.221463048081731,
      "11": 0.618489284832976,
      "12": 0.105585817820274,
      "13": 0.19513909709408
    },
    "objective_value": 6.119638340751534,
    "lower_bound": 6.119637808294565,
    "upper_bound": 6.119638340751534,
    "absolute_gap": 5.324569691822489e-07,
    "relative_gap": 8.700792201469115e-08
  },
  "performance": {
    "solution_time_seconds": 119.0830545425415,
    "solver_status": "ok",
    "termination_condition": "optimal",
    "solver": "gams",
    "subsolver": "gurobi",
    "is_relaxation": false,
    "root_relaxation_value": 0.0,
    "root_relaxation_gap_percent": 100.0,
    "relaxation_gap_percent": null,
    "absolute_gap": null
  }
}