{
  "model_parameters": {
    "n_dimensions": 2,
    "n_clusters": 3,
    "n_points": 17,
    "coord_range_lower": -1,
    "coord_range_upper": 1
  },
  "solution": {
    "status": "optimal",
    "center_coordinates": {
      "cluster_1": {
        "dim_1": -0.740614536279635,
        "dim_2": -0.677602666114179
      },
      "cluster_2": {
        "dim_1": -0.337261051290699,
        "dim_2": 0.480909715201118
      },
      "cluster_3": {
        "dim_1": 0.450512690536594,
        "dim_2": -0.397861632225413
      }
    },
    "distances": {
      "1": 0.672518365888983,
      "2": 0.197900013738988,
      "3": 0.007579435167028,
      "4": 0.13111840292361,
      "5": 0.053421767913593,
      "6": 0.313574757327085,
      "7": 0.102965424927723,
      "8": 0.082207809944478,
      "9": 0.120691101789677,
      "10": 0.071697259128605,
      "11": 0.154935061240147,
      "12": 0.170401364244043,
      "13": 0.029725895834776,
      "14": 0.048422233974315,
      "15": 0.179548052317459,
      "16": 0.237588122694524,
      "17": 0.25554996713271
    },
    "objective_value": 2.829845036187744,
    "lower_bound": 2.829845036187741,
    "absolute_gap": 3.1086244689504383e-15,
    "relative_gap": 1.0985140278699707e-15
  },
  "performance": {
    "solution_time_seconds": 5.71588921546936,
    "solver_status": "ok",
    "termination_condition": "optimal",
    "solver": "gams",
    "subsolver": "baron",
    "is_relaxation": false,
    "root_relaxation_value": 0.0,
    "root_relaxation_gap_percent": 100.0,
    "relaxation_gap_percent": null,
    "absolute_gap": null
  }
}