{
  "model_parameters": {
    "n_dimensions": 4,
    "n_clusters": 4,
    "n_points": 13,
    "coord_range_lower": -1,
    "coord_range_upper": 1
  },
  "solution": {
    "status": "optimal",
    "center_coordinates": {
      "cluster_1": {
        "dim_1": -0.457768740306158,
        "dim_2": -0.140063268227566,
        "dim_3": 0.598790402503894,
        "dim_4": 0.568417143095383
      },
      "cluster_2": {
        "dim_1": -0.410531420512931,
        "dim_2": -0.230815003098675,
        "dim_3": -0.5092135654896,
        "dim_4": -0.289412814442671
      },
      "cluster_3": {
        "dim_1": 0.634177214515635,
        "dim_2": 0.627794455563738,
        "dim_3": 0.715783691938002,
        "dim_4": 0.065614772665545
      },
      "cluster_4": {
        "dim_1": 0.807835088024092,
        "dim_2": 0.880209081200483,
        "dim_3": -0.722449320718835,
        "dim_4": -0.848615909689506
      }
    },
    "distances": {
      "1": 0.270657351366893,
      "2": 0.167663954973504,
      "3": 0.717439887120221,
      "4": 1.058299769378495,
      "5": 0.242059707780581,
      "6": 1.10940583766737,
      "7": 0.931035817614254,
      "8": 0.430476020358546,
      "9": 0.744621016033768,
      "10": 0.246670686271901,
      "11": 0.0,
      "12": 0.356594571716384,
      "13": 0.680126616297271
    },
    "objective_value": 6.955051236579188,
    "lower_bound": 2.453827096801414,
    "upper_bound": 6.955051236579188,
    "absolute_gap": 4.501224139777774,
    "relative_gap": 1.8343689111776298
  },
  "performance": {
    "solution_time_seconds": 301.26976108551025,
    "solver_status": "ok",
    "termination_condition": "optimal",
    "solver": "gams",
    "subsolver": "scip",
    "is_relaxation": false,
    "root_relaxation_value": 2.45382709680141,
    "root_relaxation_gap_percent": 64.71877757138833,
    "relaxation_gap_percent": null,
    "absolute_gap": null
  }
}