{
  "model_parameters": {
    "n_dimensions": 5,
    "n_clusters": 3,
    "n_points": 15,
    "coord_range_lower": -1,
    "coord_range_upper": 1
  },
  "solution": {
    "status": "optimal",
    "center_coordinates": {
      "cluster_1": {
        "dim_1": -0.191322968357801,
        "dim_2": 0.183238381508442,
        "dim_3": -0.570582343814059,
        "dim_4": 0.090682883131802,
        "dim_5": -0.879599365334081
      },
      "cluster_2": {
        "dim_1": 0.421124139875648,
        "dim_2": 0.031835836747766,
        "dim_3": -0.029421305544316,
        "dim_4": 0.396552991511941,
        "dim_5": 0.668626166096531
      },
      "cluster_3": {
        "dim_1": 0.421124139875648,
        "dim_2": -0.033122654668956,
        "dim_3": 0.332914211475203,
        "dim_4": -0.746072324005024,
        "dim_5": -0.179885615480376
      }
    },
    "distances": {
      "1": 0.448596772709263,
      "2": 0.624982902754933,
      "3": 0.344461053807406,
      "4": 0.248556559597776,
      "5": 1.114664992745751,
      "6": 1.139782821952371,
      "7": 1.441453945553579,
      "8": 1.262070227139994,
      "9": 1.546030275999376,
      "10": 0.776182981957069,
      "11": 0.448596741846616,
      "12": 1.112122113994532,
      "13": 0.48998775849439,
      "14": 1.208403897468257,
      "15": 0.64793190604828
    },
    "objective_value": 12.853824952069592,
    "lower_bound": 12.853824952069594,
    "absolute_gap": -1.7763568394002505e-15,
    "relative_gap": -1.3819675046331164e-16
  },
  "performance": {
    "solution_time_seconds": 50.43841481208801,
    "solver_status": "ok",
    "termination_condition": "optimal",
    "solver": "gams",
    "subsolver": "baron",
    "is_relaxation": false,
    "root_relaxation_value": 2.59149,
    "root_relaxation_gap_percent": 79.83876387251762,
    "relaxation_gap_percent": null,
    "absolute_gap": null
  }
}