{
  "model_parameters": {
    "n_dimensions": 2,
    "n_clusters": 4,
    "n_points": 13,
    "coord_range_lower": -1,
    "coord_range_upper": 1
  },
  "solution": {
    "status": "optimal",
    "center_coordinates": {
      "cluster_1": {
        "dim_1": -0.827468170828458,
        "dim_2": 0.446037436981536
      },
      "cluster_2": {
        "dim_1": -0.089014753495584,
        "dim_2": 0.202417059407578
      },
      "cluster_3": {
        "dim_1": 0.770383773791149,
        "dim_2": -0.022836360945831
      },
      "cluster_4": {
        "dim_1": 0.912092480143313,
        "dim_2": -0.780737202011272
      }
    },
    "distances": {
      "1": 0.011794850942774,
      "2": 0.022471045386512,
      "3": 0.133056345157205,
      "4": 0.101213624964373,
      "5": 0.133056360831017,
      "6": 0.117010333290972,
      "7": 0.218336472969763,
      "8": 0.007016838671838,
      "9": 0.044214560384434,
      "10": 0.051063441150923,
      "11": -9.998513e-09,
      "12": 0.032442515445673,
      "13": 0.081847492241188
    },
    "objective_value": 0.953523871438159,
    "lower_bound": 0.953523871438159,
    "absolute_gap": 0.0,
    "relative_gap": 0.0
  },
  "performance": {
    "solution_time_seconds": 588.7012331485748,
    "solver_status": "ok",
    "termination_condition": "optimal",
    "solver": "gams",
    "subsolver": "scip",
    "is_relaxation": false,
    "root_relaxation_value": 0.953523871438159,
    "root_relaxation_gap_percent": 0.0,
    "relaxation_gap_percent": null,
    "absolute_gap": null
  }
}