{
  "model_parameters": {
    "n_dimensions": 2,
    "n_clusters": 5,
    "n_points": 10,
    "coord_range_lower": -1,
    "coord_range_upper": 1
  },
  "solution": {
    "status": "optimal",
    "center_coordinates": {
      "cluster_1": {
        "dim_1": -0.921218114614516,
        "dim_2": 0.951341430419368
      },
      "cluster_2": {
        "dim_1": -0.765327074491273,
        "dim_2": -0.280510214593206
      },
      "cluster_3": {
        "dim_1": -0.455742409074605,
        "dim_2": -0.929374936380371
      },
      "cluster_4": {
        "dim_1": -0.359982130864731,
        "dim_2": 0.556877851270467
      },
      "cluster_5": {
        "dim_1": 0.563460215007254,
        "dim_2": 0.012022504381064
      }
    },
    "distances": {
      "1": 0.021482514164838,
      "2": 0.01824715679357,
      "3": 0.031638468012075,
      "4": 0.03284366551003,
      "5": 0.018135098717324,
      "6": 0.0,
      "7": 0.063317355273189,
      "8": 0.032827826409531,
      "9": 0.0,
      "10": 0.01317979556194
    },
    "objective_value": 0.231671880442497,
    "lower_bound": 0.231671880442497,
    "absolute_gap": 0.0,
    "relative_gap": 0.0
  },
  "performance": {
    "solution_time_seconds": 3.3290059566497803,
    "solver_status": "ok",
    "termination_condition": "optimal",
    "solver": "gams",
    "subsolver": "baron",
    "is_relaxation": false,
    "root_relaxation_value": 0.0,
    "root_relaxation_gap_percent": 100.0,
    "relaxation_gap_percent": null,
    "absolute_gap": null
  }
}