{
  "model_parameters": {
    "n_dimensions": 3,
    "n_clusters": 4,
    "n_points": 17,
    "coord_range_lower": -1,
    "coord_range_upper": 1
  },
  "solution": {
    "status": "optimal",
    "center_coordinates": {
      "cluster_1": {
        "dim_1": -0.863978576709441,
        "dim_2": -0.442266728693465,
        "dim_3": 0.945954120656563
      },
      "cluster_2": {
        "dim_1": 0.265140754730901,
        "dim_2": -0.225816270061011,
        "dim_3": 0.79106787088194
      },
      "cluster_3": {
        "dim_1": 0.291427489491177,
        "dim_2": -0.629575050480827,
        "dim_3": -0.396675185570854
      },
      "cluster_4": {
        "dim_1": 0.703283160372266,
        "dim_2": 0.487477419411885,
        "dim_3": 0.003007228979326
      }
    },
    "distances": {
      "1": 0.367762238972394,
      "2": 0.03782235183197,
      "3": 0.279778167235548,
      "4": 0.816452931366892,
      "5": 0.039787714776614,
      "6": 0.219153286277617,
      "7": 0.568406413064784,
      "8": 0.131620735490562,
      "9": 0.978096245664429,
      "10": 0.554142018489526,
      "11": 0.441274473937835,
      "12": 0.706494308961341,
      "13": 0.235441755122789,
      "14": 0.574623572617265,
      "15": 0.276829738030873,
      "16": 0.924798041394888,
      "17": 0.219153220571561
    },
    "objective_value": 7.371637213806888,
    "lower_bound": 7.371637213806885,
    "absolute_gap": 3.552713678800501e-15,
    "relative_gap": 4.819436409792875e-16
  },
  "performance": {
    "solution_time_seconds": 62.384934186935425,
    "solver_status": "ok",
    "termination_condition": "optimal",
    "solver": "gams",
    "subsolver": "baron",
    "is_relaxation": false,
    "root_relaxation_value": 0.0492823,
    "root_relaxation_gap_percent": 99.33146058913893,
    "relaxation_gap_percent": null,
    "absolute_gap": null
  }
}