{
  "model_parameters": {
    "n_dimensions": 4,
    "n_clusters": 5,
    "n_points": 12,
    "coord_range_lower": -1,
    "coord_range_upper": 1
  },
  "solution": {
    "status": "feasible",
    "center_coordinates": {
      "cluster_1": {
        "dim_1": -0.661884877837143,
        "dim_2": -0.444427280961809,
        "dim_3": -0.004480495888291,
        "dim_4": -0.375173341942558
      },
      "cluster_2": {
        "dim_1": -0.402482775142875,
        "dim_2": 0.426579131586757,
        "dim_3": 0.430166151366383,
        "dim_4": 0.446077241187101
      },
      "cluster_3": {
        "dim_1": -0.025785063240748,
        "dim_2": 0.278486890954247,
        "dim_3": -0.53244690499925,
        "dim_4": 0.304225461178178
      },
      "cluster_4": {
        "dim_1": 0.624708272260468,
        "dim_2": -0.449671982080796,
        "dim_3": 0.36131254181393,
        "dim_4": 0.954210359223466
      },
      "cluster_5": {
        "dim_1": 0.657425142506789,
        "dim_2": -0.858542480437034,
        "dim_3": -0.09493375657063,
        "dim_4": -0.745699256767104
      }
    },
    "distances": {
      "1": 0.135137976298287,
      "2": 0.311634374463663,
      "3": 0.287246824937749,
      "4": 0.245572520918484,
      "5": 0.368115324043905,
      "6": 0.366807786647527,
      "7": 0.0,
      "8": 0.287657595372085,
      "9": 0.136080712904561,
      "10": 0.494219958601616,
      "11": 0.321197037439876,
      "12": 0.525198480300828
    },
    "objective_value": 3.478868591928581,
    "lower_bound": 2.266819609403203,
    "upper_bound": 3.47886859192858,
    "absolute_gap": 1.2120489825253782,
    "relative_gap": 0.5346914141282202
  },
  "performance": {
    "solution_time_seconds": 300.6854462623596,
    "solver_status": "ok",
    "termination_condition": "feasible",
    "solver": "gams",
    "subsolver": "gurobi",
    "is_relaxation": false,
    "root_relaxation_value": 0.0,
    "root_relaxation_gap_percent": 100.0,
    "relaxation_gap_percent": null,
    "absolute_gap": null
  }
}