{
  "model_parameters": {
    "n_dimensions": 5,
    "n_clusters": 5,
    "n_points": 10,
    "coord_range_lower": -1,
    "coord_range_upper": 1
  },
  "solution": {
    "status": "optimal",
    "center_coordinates": {
      "cluster_1": {
        "dim_1": -0.969866907514816,
        "dim_2": -0.891713616849959,
        "dim_3": 0.047855545203109,
        "dim_4": -0.02973001318974,
        "dim_5": -0.330527141546089
      },
      "cluster_2": {
        "dim_1": -0.70568239150671,
        "dim_2": 0.664605519441957,
        "dim_3": -0.195992256592971,
        "dim_4": -0.133546931526985,
        "dim_5": -0.110565044856277
      },
      "cluster_3": {
        "dim_1": 0.275861850856111,
        "dim_2": -0.684052792661715,
        "dim_3": 0.881440169903647,
        "dim_4": 0.099373191971863,
        "dim_5": 0.58714283631873
      },
      "cluster_4": {
        "dim_1": 0.443816675869899,
        "dim_2": 0.208819125824498,
        "dim_3": -0.282131117578159,
        "dim_4": 0.440711611160607,
        "dim_5": -0.634433684306202
      },
      "cluster_5": {
        "dim_1": 0.930915430312985,
        "dim_2": 0.861788980755961,
        "dim_3": 0.047017309097749,
        "dim_4": -0.076565696792134,
        "dim_5": -0.439407201361767
      }
    },
    "distances": {
      "1": 0.439135767482516,
      "2": 0.0,
      "3": 0.574962100885822,
      "4": 0.435906404654912,
      "5": 0.199955919494362,
      "6": 0.221104992945733,
      "7": 0.279440024968142,
      "8": 0.178253016653814,
      "9": 0.0,
      "10": 0.178253023430943
    },
    "objective_value": 2.507011250516244,
    "lower_bound": 2.507011250516245,
    "upper_bound": 2.507011250516245,
    "absolute_gap": -8.881784197001252e-16,
    "relative_gap": -3.542777957287711e-16
  },
  "performance": {
    "solution_time_seconds": 282.5520794391632,
    "solver_status": "ok",
    "termination_condition": "optimal",
    "solver": "gams",
    "subsolver": "baron",
    "is_relaxation": false,
    "root_relaxation_value": 0.0,
    "root_relaxation_gap_percent": 100.0,
    "relaxation_gap_percent": null,
    "absolute_gap": null
  }
}