{
  "model_parameters": {
    "n_dimensions": 2,
    "n_clusters": 3,
    "n_points": 10,
    "coord_range_lower": -1,
    "coord_range_upper": 1
  },
  "solution": {
    "status": "optimal",
    "center_coordinates": {
      "cluster_1": {
        "dim_1": -0.401726962131112,
        "dim_2": 0.509448976945532
      },
      "cluster_2": {
        "dim_1": -0.228629601461606,
        "dim_2": -0.889400582641823
      },
      "cluster_3": {
        "dim_1": 0.911050666878836,
        "dim_2": -0.126707688451844
      }
    },
    "distances": {
      "1": 0.334743815087001,
      "2": 0.25874874248375,
      "3": 0.141282568089505,
      "4": 0.371914297086364,
      "5": 0.021964597891072,
      "6": 0.335353441358265,
      "7": 0.084364275640728,
      "8": 0.033921253408549,
      "9": 0.167279184008042,
      "10": 0.030486681651447
    },
    "objective_value": 1.780058856704723,
    "lower_bound": 1.780057246291349,
    "absolute_gap": 1.6104133739869297e-06,
    "relative_gap": 9.046975187692065e-07
  },
  "performance": {
    "solution_time_seconds": 4.104832649230957,
    "solver_status": "ok",
    "termination_condition": "optimal",
    "solver": "gams",
    "subsolver": "gurobi",
    "is_relaxation": false,
    "root_relaxation_value": 0.0,
    "root_relaxation_gap_percent": 100.0,
    "relaxation_gap_percent": null,
    "absolute_gap": null
  }
}